structured_errors/__init__.py
structured_errors-0.0.1.dist-info/WHEEL
structured_errors-0.0.1.dist-info/METADATA
structured_errors-0.0.1.dist-info/RECORD
